Workbook

Sheet RAW_Financial
A1: Fiscal_Year | B1: Period_End | C1: Total_Revenue_M | D1: COGS_M | E1: Gross_Profit_M | F1: Gross_Margin_Pct | G1: Operating_Income_M | H1: Operating_Margin_Pct | I1: Net_Income_M | J1: Net_Margin_Pct | K1: SGA_Expenses_M | L1: SGA_Pct_Revenue
A2: 2015 | B2: 42155 | C2: 30601 | D2: 16534 | E2: 14067 | F2: 45.97 | G2: 4173 | H2: 13.64 | I2: 3273 | J2: 10.7 | K2: 8766 | L2: 28.64
A3: 2016 | B3: 42521 | C3: 32376 | D3: 17405 | E3: 14971 | F3: 46.24 | G3: 4503 | H3: 13.91 | I3: 3760 | J3: 11.61 | K3: 9892 | L3: 30.55
A4: 2017 | B4: 42886 | C4: 34350 | D4: 19038 | E4: 15312 | F4: 44.58 | G4: 4748 | H4: 13.83 | I4: 4240 | J4: 12.34 | K4: 10563 | L4: 30.75
A5: 2018 | B5: 43251 | C5: 36397 | D5: 20441 | E5: 15956 | F5: 43.84 | G5: 4445 | H5: 12.21 | I5: 1933 | J5: 5.31 | K5: 10962 | L5: 30.12
A6: 2019 | B6: 43616 | C6: 39117 | D6: 21643 | E6: 17474 | F6: 44.67 | G6: 4772 | H6: 12.2 | I6: 4029 | J6: 10.3 | K6: 11534 | L6: 29.49
A7: 2020 | B7: 43982 | C7: 37403 | D7: 21162 | E7: 16241 | F7: 43.42 | G7: 3114 | H7: 8.33 | I7: 2539 | J7: 6.79 | K7: 11736 | L7: 31.38
A8: 2021 | B8: 44347 | C8: 44538 | D8: 24576 | E8: 19962 | F8: 44.82 | G8: 6942 | H8: 15.58 | I8: 5727 | J8: 12.86 | K8: 13045 | L8: 29.29
A9: 2022 | B9: 44712 | C9: 46710 | D9: 25231 | E9: 21479 | F9: 45.98 | G9: 6680 | H9: 14.29 | I9: 6046 | J9: 12.94 | K9: 14804 | L9: 31.69
A10: 2023 | B10: 45077 | C10: 51217 | D10: 28925 | E10: 22292 | F10: 43.52 | G10: 5921 | H10: 11.55 | I10: 5070 | J10: 9.9 | K10: 16377 | L10: 31.98
A11: 2024 | B11: 45443 | C11: 51362 | D11: 28475 | E11: 22887 | F11: 44.56 | G11: 6317 | H11: 12.29 | I11: 5700 | J11: 11.1 | K11: 16576 | L11: 32.27

Sheet RAW_Channel
A1: Fiscal_Year | B1: Total_Nike_Brand_Revenue_M | C1: Nike_Direct_Revenue_M | D1: Wholesale_Revenue_M | E1: Digital_Revenue_M | F1: Nike_Direct_Share_Pct | G1: Wholesale_Share_Pct | H1: CDO_Phase | I1: Key_Event | J1: Column1 | K1: Column2 | L1: Column3 | M1: Column4
A2: 2015 | B2: 29500 | C2: 8100 | D2: 21400 | E2: 1100 | F2: 27.5 | G2: 72.5 | H2: Pre-CDO | I2: DTC growing organically
A3: 2016 | B3: 32014 | C3: 9000 | D3: 23014 | E3: 1400 | F3: 28.1 | G3: 71.9 | H3: Pre-CDO | I3: CDO concept forming internally
A4: 2017 | B4: 33990 | C4: 11000 | D4: 22990 | E4: 2200 | F4: 32.4 | G4: 67.6 | H4: CDO Launch | I4: Consumer Direct Offense announced June 2017
A5: 2018 | B5: 35750 | C5: 12400 | D5: 23350 | E5: 2700 | F5: 34.7 | G5: 65.3 | H5: CDO Acceleration | I5: Major wholesale partner cuts begin
A6: 2019 | B6: 38985 | C6: 11800 | D6: 27185 | E6: 3000 | F6: 30.3 | G6: 69.7 | H6: CDO Acceleration | I6: Partnership with Amazon; further retailer cuts
A7: 2020 | B7: 37403 | C7: 12400 | D7: 25003 | E7: 3500 | F7: 33.2 | G7: 66.8 | H7: CDO + COVID | I7: COVID accelerates digital; stores closed
A8: 2021 | B8: 44436 | C8: 16400 | D8: 28036 | E8: 7400 | F8: 36.9 | G8: 63.1 | H8: CDA Launch | I8: Consumer Direct Acceleration replaces CDO
A9: 2022 | B9: 44436 | C9: 18726 | D9: 25608 | E9: 8600 | F9: 42.1 | G9: 57.9 | H9: CDA Peak | I9: 50000+ wholesale accounts cut; inventory crisis begins
A10: 2023 | B10: 48763 | C10: 21308 | D10: 27397 | E10: 12400 | F10: 43.7 | G10: 56.2 | H10: Crisis | I10: Inventory glut; heavy discounting; Hoka/On surging
A11: 2024 | B11: 49322 | C11: 21519 | D11: 27758 | E11: 12100 | F11: 43.6 | G11: 56.3 | H11: Reckoning | I11: CEO Donahoe out; wholesale return strategy begins

Sheet RAW_ProductMarket
A1: Year | B1: Nike_Athletic_Footwear_Share_Pct | C1: Adidas_Share_Pct | D1: Hoka_Share_Pct | E1: On_Running_Share_Pct | F1: New_Balance_Share_Pct | G1: Under_Armour_Share_Pct | H1: Nike_D2C_Pct | I1: Adidas_D2C_Pct | J1: Nike_Digital_Revenue_M | K1: Adidas_Digital_Revenue_M
A2: 2017 | B2: 38.2 | C2: 20.1 | D2: 0.8 | E2: 0.3 | F2: 5.2 | G2: 7.5 | H2: 32.4 | I2: 22 | J2: 2200 | K2: 1600
A3: 2018 | B3: 37.5 | C3: 20.8 | D3: 1.1 | E3: 0.5 | F3: 5.5 | G3: 7.1 | H3: 34.7 | I3: 23 | J3: 2700 | K3: 1900
A4: 2019 | B4: 36.9 | C4: 21.4 | D4: 1.6 | E4: 0.8 | F4: 5.8 | G4: 6.8 | H4: 30.3 | I4: 24 | J4: 3000 | K4: 2200
A5: 2020 | B5: 35.8 | C5: 22 | D5: 2.3 | E5: 1.2 | F5: 6.1 | G5: 6.2 | H5: 33.2 | I5: 26 | J5: 3500 | K5: 2700
A6: 2021 | B6: 34.3 | C6: 22.5 | D6: 3.2 | E6: 2.1 | F6: 6.8 | G6: 5.8 | H6: 36.9 | I6: 30 | J6: 7400 | K6: 3100
A7: 2022 | B7: 33.1 | C7: 21.8 | D7: 4.8 | E7: 3.5 | F7: 7.5 | G7: 5.2 | H7: 42.1 | I7: 29 | J7: 8600 | K7: 3600
A8: 2023 | B8: 31.5 | C8: 20.9 | D8: 6.1 | E8: 5.2 | F8: 8.3 | G8: 4.8 | H8: 43.7 | I8: 28 | J8: 12400 | K8: 4100
A9: 2024 | B9: 30.2 | C9: 19.8 | D9: 7.4 | E9: 6.8 | F9: 9.1 | G9: 4.5 | H9: 43.6 | I9: 27 | J9: 12100 | K9: 4300
A12: CLV MODEL DATA
A13: Channel | B13: Avg_Order_Value_USD | C13: Purchase_Frequency_Per_Year | D13: Avg_Customer_Lifespan_Years | E13: Est_Gross_Margin_Pct | F13: Customer_Acquisition_Cost_USD | G13: Estimated_CLV_USD | H13: LTV_CAC_Ratio | I13: Retention_Rate_Pct | J13: Segment_Type
A14: Nike Direct - Digital | B14: 92 | C14: 2.4 | D14: 2.8 | E14: 47 | F14: 45 | G14: 290.57 | H14: 6.46 | I14: 58 | J14: D2C
A15: Nike Direct - Owned Stores | B15: 88 | C15: 1.9 | D15: 3.2 | E15: 44 | F15: 38 | G15: 235.42 | H15: 6.2 | I15: 62 | J15: D2C
A16: Nike SNKRS App Sneakerhead | B16: 165 | C16: 3.1 | D16: 4.5 | E16: 51 | F16: 28 | G16: 1173.89 | H16: 41.92 | I16: 71 | J16: D2C Premium
A17: Wholesale - Foot Locker | B17: 72 | C17: 1.4 | D17: 5.1 | E17: 38 | F17: 8 | G17: 195.35 | H17: 24.42 | I17: 74 | J17: Wholesale
A18: Wholesale - Sporting Goods | B18: 68 | C18: 1.6 | D18: 4.8 | E18: 37 | F18: 6 | G18: 193.23 | H18: 32.2 | I18: 72 | J18: Wholesale
A19: Wholesale - Department Store | B19: 61 | C19: 1.2 | D19: 4.2 | E19: 35 | F19: 4 | G19: 107.6 | H19: 26.9 | I19: 68 | J19: Wholesale

Sheet RAW_Stock_Events
A1: Event_ID | B1: Event_Date | C1: Event_Name | D1: Event_Category | E1: Decision_Type | F1: NKE_Price_On_Event | G1: NKE_Price_30d_After | H1: NKE_Price_90d_After | I1: Return_30d_Pct | J1: Return_90d_Pct | K1: Market_Verdict | L1: Column1
A2: 1 | B2: 42901 | C2: Consumer Direct Offense Announced | D2: Strategy | E2: Offensive | F2: 53.2 | G2: 58.1 | H2: 60.2 | I2: 9.2 | J2: 13.2 | K2: Positive
A3: 2 | B3: 43158 | C3: Partnership with Amazon Confirmed | D3: Partnership | E3: Offensive | F3: 66.5 | G3: 69.3 | H3: 72.1 | I3: 4.2 | J3: 8.4 | K3: Positive
A4: 3 | B4: 43781 | C4: Mark Parker Steps Down - Donahoe Named CEO | D4: Leadership | E4: Transition | F4: 90.3 | G4: 87.2 | H4: 93.4 | I4: -3.4 | J4: 3.4 | K4: Neutral
A5: 4 | B5: 44005 | C5: Consumer Direct Acceleration Announced | D5: Strategy | E5: Acceleration | F5: 98.3 | G5: 110.2 | H5: 119.4 | I5: 12.1 | J5: 21.5 | K5: Positive
A6: 5 | B6: 44518 | C6: NKE Stock Peak ~$177 | D6: Market | E6: Peak | F6: 177.5 | G6: 155.3 | H6: 134.2 | I6: -12.5 | J6: -24.4 | K6: N/A - Peak
A7: 6 | B7: 44736 | C7: Inventory Crisis Disclosed in Earnings | D7: Crisis | E7: Warning | F7: 109.5 | G7: 97.3 | H7: 85.2 | I7: -11.1 | J7: -22.2 | K7: Negative
A8: 7 | B8: 44911 | C8: Q2 FY2023 Earnings - Inventory Glut Confirmed | D8: Crisis | E8: Earnings | F8: 110.2 | G8: 118.4 | H8: 122.3 | I8: 7.4 | J8: 11 | K8: Mixed
A9: 8 | B9: 45203 | C9: Foot Locker CEO Announces Renewed Nike Partnership | D9: Recovery | E9: Partnership | F9: 88.5 | G9: 100.2 | H9: 105.4 | I9: 13.2 | J9: 19.1 | K9: Positive
A10: 9 | B10: 45471 | C10: FY2024 Earnings - Revenue Growth Stalls | D10: Crisis | E10: Earnings | F10: 75.3 | G10: 72.1 | H10: 70.2 | I10: -4.3 | J10: -6.8 | K10: Negative
A11: 10 | B11: 45554 | C11: Donahoe Replaced by Elliott Hill as CEO | D11: Leadership | E11: Recovery | F11: 78.2 | G11: 90.4 | H11: 96.3 | I11: 15.6 | J11: 23.1 | K11: Positive
A12: 11 | B12: 45566 | C12: Elliott Management Takes Activist Stake | D12: Investor | E12: External | F12: 92.1 | G12: 85.3 | H12: 80.2 | I12: -7.4 | J12: -13 | K12: Negative
A15: QUARTERLY DETAIL DATA
A16: Fiscal_Year | B16: Quarter | C16: Period_End | D16: Revenue_M | E16: Gross_Profit_M | F16: Gross_Margin_Pct | G16: Operating_Income_M | H16: Operating_Margin_Pct | I16: Nike_Direct_Revenue_M | J16: Wholesale_Revenue_M | K16: Inventory_M | L16: Column1
A17: 2019 | B17: Q1 | C17: 43343 | D17: 9949 | E17: 4371 | F17: 43.9 | G17: 1207 | H17: 12.1 | I17: 3062 | J17: 6887 | K17: 5007
A18: 2019 | B18: Q2 | C18: 43434 | D18: 9374 | E18: 4105 | F18: 43.8 | G18: 849 | H18: 9.1 | I18: 2900 | J18: 6474 | K18: 5622
A19: 2019 | B19: Q3 | C19: 43524 | D19: 9609 | E19: 4339 | F19: 45.2 | G19: 1263 | H19: 13.1 | I19: 2840 | J19: 6769 | K19: 5254
A20: 2019 | B20: Q4 | C20: 43616 | D20: 10185 | E20: 4633 | F20: 45.5 | G20: 1453 | H20: 14.3 | I20: 3098 | J20: 7087 | K20: 5622
A21: 2020 | B21: Q1 | C21: 43708 | D21: 10660 | E21: 4544 | F21: 42.6 | G21: 1374 | H21: 12.9 | I21: 3271 | J21: 7389 | K21: 5879
A22: 2020 | B22: Q2 | C22: 43799 | D22: 10330 | E22: 4847 | F22: 46.9 | G22: 1330 | H22: 12.9 | I22: 3163 | J22: 7167 | K22: 5724
A23: 2020 | B23: Q3 | C23: 43890 | D23: 10100 | E23: 4473 | F23: 44.3 | G23: 1003 | H23: 9.9 | I23: 2960 | J23: 7140 | K23: 6498
A24: 2020 | B24: Q4 | C24: 43982 | D24: 6313 | E24: 2353 | F24: 37.3 | G24: -790 | H24: -12.5 | I24: 3006 | J24: 3307 | K24: 7520
A25: 2021 | B25: Q1 | C25: 44074 | D25: 10590 | E25: 4741 | F25: 44.8 | G25: 1503 | H25: 14.2 | I25: 3558 | J25: 7032 | K25: 7488
A26: 2021 | B26: Q2 | C26: 44165 | D26: 11240 | E26: 4847 | F26: 43.1 | G26: 1503 | H26: 13.4 | I26: 3980 | J26: 7260 | K26: 6705
A27: 2021 | B27: Q3 | C27: 44255 | D27: 10357 | E27: 4719 | F27: 45.6 | G27: 1449 | H27: 14 | I27: 3597 | J27: 6760 | K27: 6854
A28: 2021 | B28: Q4 | C28: 44347 | D28: 12344 | E28: 5655 | F28: 45.8 | G28: 2487 | H28: 20.1 | I28: 5265 | J28: 7079 | K28: 6854
... A40: 2024 | B40: Q4 | C40: 45443 | D40: 12614 | E40: 5634 | F40: 44.7 | G40: 1885 | H40: 14.9 | I40: 6367 | J40: 6153 | K40: 7519
A43: SCENARIO FORECAST DATA
A44: Fiscal_Year | B44: Actual_Revenue_M | C44: Actual_Op_Margin_Pct | D44: ScenarioA_Balanced_Revenue_M | E44: ScenarioA_Op_Margin_Pct | F44: ScenarioB_Actual_Revenue_M | G44: ScenarioB_Op_Margin_Pct | H44: ScenarioC_Recovery_Revenue_M | I44: ScenarioC_Op_Margin_Pct | J44: Notes | K44: Column1 | L44: Column2
A45: 2017 | B45: 34350 | C45: 13.83 | D45: 34350 | E45: 13.83 | F45: 34350 | G45: 13.83 | H45: 34350 | I45: 13.83 | J45: Base year - CDO just announced
A46: 2018 | B46: 36397 | C46: 12.21 | D46: 37100 | E46: 13.5 | F46: 36397 | G46: 12.21 | H46: 36397 | I46: 12.21 | J46: Scenario A: retained more wholesale
A47: 2019 | B47: 39117 | C47: 12.2 | D47: 41000 | E47: 13.8 | F47: 39117 | G47: 12.2 | H47: 39117 | I47: 12.2 | J47: Scenario A: balanced growth without aggressive cuts
A48: 2020 | B48: 37403 | C48: 8.33 | D48: 39500 | E48: 11.5 | F48: 37403 | G48: 8.33 | H48: 37403 | I48: 8.33 | J48: COVID impact - Scenario A slightly better
A49: 2021 | B49: 44538 | C49: 15.58 | D49: 46000 | E49: 15.2 | F49: 44538 | G49: 15.58 | H49: 44538 | I49: 15.58 | J49: Boom year - all scenarios similar
A50: 2022 | B50: 46710 | C50: 14.29 | D50: 50500 | E50: 14.8 | F50: 46710 | G50: 14.29 | H50: 46710 | I50: 14.29 | J50: Scenario A: no inventory crisis
A51: 2023 | B51: 51217 | C51: 11.55 | D51: 54000 | E51: 13.4 | F51: 51217 | G51: 11.55 | H51: 52000 | I51: 12.5 | J51: Gap widens in Scenario A
A52: 2024 | B52: 51362 | C52: 12.29 | D52: 57000 | E52: 14.2 | F52: 51362 | G52: 12.29 | H52: 54000 | I52: 13.1 | J52: $5.6B revenue missed vs Scenario A
A53: 2025 | B53: 47818 | C53: 10.3 | D53: 59500 | E53: 14.8 | F53: 47818 | G53: 10.3 | H53: 56000 | I53: 13.8 | J53: Actual declining; scenarios project forward
A54: 2026 | B54: 46398 | C54: 7.99 | D54: 62000 | E54: 15.2 | F54: 48000 | G54: 10.5 | H54: 58500 | I54: 14 | J54: Hypothetical projection
A55: 2027 | B55: N/A | C55: N/A | D55: 65000 | E55: 15.8 | F55: 50000 | G55: 11.2 | H55: 61000 | I55: 14.5 | J55: Full forecast - hypothetical only

Sheet CALC_ChannelModel
A1: Fiscal_Year | B1: Total_Revenue_M | C1: DTC_Revenue_M | D1: Wholesale_Revenue_M | E1: DTC_Share_Pct | F1: Wholesale_Share_Pct | G1: DTC_Growth_YoY_Pct | H1: Wholesale_Growth_YoY_Pct | I1: Gross_Margin_Pct | J1: Operating_Margin_Pct | K1: SGA_Pct_Revenue | L1: Strategy_Phase | M1: Margin_Change_Bps | N1: DTC_Revenue_Indexed | O1: Wholesale_Revenue_Indexed
A2: {=tbl_Channel[Fiscal_Year]} -> 2015 | B2: {=tbl_Channel[Total_Nike_Brand_Revenue_M]} -> 29500 | C2: {=tbl_Channel[Nike_Direct_Revenue_M]} -> 8100 | D2: {=tbl_Channel[Wholesale_Revenue_M]} -> 21400 | E2: {=tbl_Channel[Nike_Direct_Share_Pct]} -> 27.5 | F2: {=tbl_Channel[Wholesale_Share_Pct]} -> 72.5 | G2: =NA() -> #N/A | H2: =NA() -> #N/A | I2: {=tbl_Financial[Gross_Margin_Pct]} -> 45.97 | J2: {=tbl_Financial[Operating_Margin_Pct]} -> 13.64 | K2: {=tbl_Financial[SGA_Pct_Revenue]} -> 28.64 | L2: {=tbl_Channel[CDO_Phase]} -> Pre-CDO | M2: =NA() -> #N/A | N2: =NA() -> #N/A | O2: =NA() -> #N/A
A3: 2016 | B3: 32014 | C3: 9000 | D3: 23014 | E3: 28.1 | F3: 71.9 | G3: =ROUND(((C3-C2)/C2)*100,2) -> 11.11 | H3: =ROUND(((D3-D2)/D2)*100,2) -> 7.54 | I3: 46.24 | J3: 13.91 | K3: 30.55 | L3: Pre-CDO | M3: =ROUND((J3-J2)*100,1) -> 27 | N3: =NA() -> #N/A | O3: =NA() -> #N/A
A4: 2017 | B4: 33990 | C4: 11000 | D4: 22990 | E4: 32.4 | F4: 67.6 | G4: =ROUND(((C4-C3)/C3)*100,2) -> 22.22 | H4: =ROUND(((D4-D3)/D3)*100,2) -> -0.1 | I4: 44.58 | J4: 13.83 | K4: 30.75 | L4: CDO Launch | M4: =ROUND((J4-J3)*100,1) -> -8 | N4: =100 -> 100 | O4: 100
A5: 2018 | B5: 35750 | C5: 12400 | D5: 23350 | E5: 34.7 | F5: 65.3 | G5: =ROUND(((C5-C4)/C4)*100,2) -> 12.73 | H5: =ROUND(((D5-D4)/D4)*100,2) -> 1.57 | I5: 43.84 | J5: 12.21 | K5: 30.12 | L5: CDO Acceleration | M5: =ROUND((J5-J4)*100,1) -> -162 | N5: =ROUND((C5/C$4)*100,1) -> 112.7 | O5: =ROUND((D5/D$4)*100,1) -> 101.6
A6: 2019 | B6: 38985 | C6: 11800 | D6: 27185 | E6: 30.3 | F6: 69.7 | G6: =ROUND(((C6-C5)/C5)*100,2) -> -4.84 | H6: =ROUND(((D6-D5)/D5)*100,2) -> 16.42 | I6: 44.67 | J6: 12.2 | K6: 29.49 | L6: CDO Acceleration | M6: =ROUND((J6-J5)*100,1) -> -1 | N6: =ROUND((C6/C$4)*100,1) -> 107.3 | O6: =ROUND((D6/D$4)*100,1) -> 118.2
A7: 2020 | B7: 37403 | C7: 12400 | D7: 25003 | E7: 33.2 | F7: 66.8 | G7: =ROUND(((C7-C6)/C6)*100,2) -> 5.08 | H7: =ROUND(((D7-D6)/D6)*100,2) -> -8.03 | I7: 43.42 | J7: 8.33 | K7: 31.38 | L7: CDO + COVID | M7: =ROUND((J7-J6)*100,1) -> -387 | N7: =ROUND((C7/C$4)*100,1) -> 112.7 | O7: =ROUND((D7/D$4)*100,1) -> 108.8
A8: 2021 | B8: 44436 | C8: 16400 | D8: 28036 | E8: 36.9 | F8: 63.1 | G8: =ROUND(((C8-C7)/C7)*100,2) -> 32.26 | H8: =ROUND(((D8-D7)/D7)*100,2) -> 12.13 | I8: 44.82 | J8: 15.58 | K8: 29.29 | L8: CDA Launch | M8: =ROUND((J8-J7)*100,1) -> 725 | N8: =ROUND((C8/C$4)*100,1) -> 149.1 | O8: =ROUND((D8/D$4)*100,1) -> 121.9
A9: 2022 | B9: 44436 | C9: 18726 | D9: 25608 | E9: 42.1 | F9: 57.9 | G9: =ROUND(((C9-C8)/C8)*100,2) -> 14.18 | H9: =ROUND(((D9-D8)/D8)*100,2) -> -8.66 | I9: 45.98 | J9: 14.29 | K9: 31.69 | L9: CDA Peak | M9: =ROUND((J9-J8)*100,1) -> -129 | N9: =ROUND((C9/C$4)*100,1) -> 170.2 | O9: =ROUND((D9/D$4)*100,1) -> 111.4
A10: 2023 | B10: 48763 | C10: 21308 | D10: 27397 | E10: 43.7 | F10: 56.2 | G10: =ROUND(((C10-C9)/C9)*100,2) -> 13.79 | H10: =ROUND(((D10-D9)/D9)*100,2) -> 6.99 | I10: 43.52 | J10: 11.55 | K10: 31.98 | L10: Crisis | M10: =ROUND((J10-J9)*100,1) -> -274 | N10: =ROUND((C10/C$4)*100,1) -> 193.7 | O10: =ROUND((D10/D$4)*100,1) -> 119.2
A11: 2024 | B11: 49322 | C11: 21519 | D11: 27758 | E11: 43.6 | F11: 56.3 | G11: =ROUND(((C11-C10)/C10)*100,2) -> 0.99 | H11: =ROUND(((D11-D10)/D10)*100,2) -> 1.32 | I11: 44.56 | J11: 12.29 | K11: 32.27 | L11: Reckoning | M11: =ROUND((J11-J10)*100,1) -> 74 | N11: =ROUND((C11/C$4)*100,1) -> 195.6 | O11: =ROUND((D11/D$4)*100,1) -> 120.7
A14: SCENARIO FORECAST DATA
A15: Fiscal_Year | B15: Actual_Revenue_M | C15: ScenarioA_Balanced_Revenue_M | D15: ScenarioC_Recovery_Revenue_M | E15: Actual_Op_Margin_Pct | F15: ScenarioA_Op_Margin_Pct | G15: ScenarioC_Op_Margin_Pct | H15: Revenue_Gap_vs_ScenarioA_M
B16: 34350 | C16: 34350 | H16: =C16-B16 -> 0
B17: 36397 | C17: 37100 | H17: =C17-B17 -> 703
B18: 39117 | C18: 41000 | H18: =C18-B18 -> 1883
B19: 37403 | C19: 39500 | H19: =C19-B19 -> 2097
B20: 44538 | C20: 46000 | H20: =C20-B20 -> 1462
B21: 46710 | C21: 50500 | H21: =C21-B21 -> 3790
B22: 51217 | C22: 54000 | H22: =C22-B22 -> 2783
B23: 51362 | C23: 57000 | H23: =C23-B23 -> 5638
B24: 47818 | C24: 59500 | H24: =C24-B24 -> 11682
B25: 46398 | C25: 62000 | H25: =C25-B25 -> 15602
B26: N/A | C26: 65000 | H26: =C26-B26 -> #VALUE!

Sheet CALC_CustomerCLV
A1: Channel | B1: Segment_Type | C1: Avg_Order_Value_USD | D1: Purchase_Frequency_Per_Year | E1: Avg_Customer_Lifespan_Years | F1: Est_Gross_Margin_Pct | G1: Customer_Acquisition_Cost_USD | H1: Estimated_CLV_USD | I1: LTV_CAC_Ratio | J1: Retention_Rate_Pct | K1: CLV_Tier | L1: CAC_Efficiency_Score | M1: Wholesale_vs_DTC_CLV_Gap | P1: Avg_DTC_CLV
A2: {=tbl_Market1[Channel]} -> Nike Direct - Digital | B2: {=tbl_Market1[Segment_Type]} -> D2C | C2: {=tbl_Market1[Avg_Order_Value_USD]} -> 92 | D2: {=tbl_Market1[Purchase_Frequency_Per_Year]} -> 2.4 | E2: {=tbl_Market1[Avg_Customer_Lifespan_Years]} -> 2.8 | F2: {=tbl_Market1[Est_Gross_Margin_Pct]} -> 47 | G2: {=tbl_Market1[Customer_Acquisition_Cost_USD]} -> 45 | H2: {=tbl_Market1[Estimated_CLV_USD]} -> 290.57 | I2: {=tbl_Market1[LTV_CAC_Ratio]} -> 6.46 | J2: {=tbl_Market1[Retention_Rate_Pct]} -> 58 | K2: =IF(H2>=500,"High Value",IF(H2>=200,"Mid Value","Low Value")) -> Mid Value | L2: =ROUND(H2/G2,2) -> 6.46 | M2: =ROUND(H2-$P$2,2) -> 27.58 | P2: =AVERAGEIF(B2:B7,"D2C",H2:H7) -> 262.995
A3: Nike Direct - Owned Stores | B3: D2C | C3: 88 | D3: 1.9 | E3: 3.2 | F3: 44 | G3: 38 | H3: 235.42 | I3: 6.2 | J3: 62 | K3: =IF(H3>=500,"High Value",IF(H3>=200,"Mid Value","Low Value")) -> Mid Value | L3: =ROUND(H3/G3,2) -> 6.2 | M3: =ROUND(H3-$P$2,2) -> -27.58 | P3: =AVERAGEIF(B3:B8,"D2C",H3:H8) -> 235.42
A4: Nike SNKRS App Sneakerhead | B4: D2C Premium | C4: 165 | D4: 3.1 | E4: 4.5 | F4: 51 | G4: 28 | H4: 1173.89 | I4: 41.92 | J4: 71 | K4: =IF(H4>=500,"High Value",IF(H4>=200,"Mid Value","Low Value")) -> High Value | L4: =ROUND(H4/G4,2) -> 41.92 | M4: =ROUND(H4-$P$2,2) -> 910.9 | P4: =AVERAGEIF(B4:B9,"D2C",H4:H9) -> #DIV/0!
A5: Wholesale - Foot Locker | B5: Wholesale | C5: 72 | D5: 1.4 | E5: 5.1 | F5: 38 | G5: 8 | H5: 195.35 | I5: 24.42 | J5: 74 | K5: =IF(H5>=500,"High Value",IF(H5>=200,"Mid Value","Low Value")) -> Low Value | L5: =ROUND(H5/G5,2) -> 24.42 | M5: =ROUND(H5-$P$2,2) -> -67.65 | P5: =AVERAGEIF(B5:B10,"D2C",H5:H10) -> #DIV/0!
A6: Wholesale - Sporting Goods | B6: Wholesale | C6: 68 | D6: 1.6 | E6: 4.8 | F6: 37 | G6: 6 | H6: 193.23 | I6: 32.2 | J6: 72 | K6: =IF(H6>=500,"High Value",IF(H6>=200,"Mid Value","Low Value")) -> Low Value | L6: =ROUND(H6/G6,2) -> 32.21 | M6: =ROUND(H6-$P$2,2) -> -69.77 | P6: =AVERAGEIF(B6:B11,"D2C",H6:H11) -> #DIV/0!
A7: Wholesale - Department Store | B7: Wholesale | C7: 61 | D7: 1.2 | E7: 4.2 | F7: 35 | G7: 4 | H7: 107.6 | I7: 26.9 | J7: 68 | K7: =IF(H7>=500,"High Value",IF(H7>=200,"Mid Value","Low Value")) -> Low Value | L7: =ROUND(H7/G7,2) -> 26.9 | M7: =ROUND(H7-$P$2,2) -> -155.4 | P7: =AVERAGEIF(B7:B12,"D2C",H7:H12) -> #DIV/0!
A8: 0 | B8: 0 | C8: 0 | D8: 0 | E8: 0 | F8: 0 | G8: 0 | H8: 0 | I8: 0 | J8: 0
A11: CLV SENSITIVITY ANALYSIS — NIKE DIRECT DIGITAL
B13: Frequency -20% | C13: Frequency -10% | D13: Frequency Base | E13: Frequency +10% | F13: Frequency +20%
A14: AOV -20% | B14: =ROUND(($C$2*(1+(-0.2+(ROW()-14)*0.1)))*($D$2*(1+(-0.2+(COLUMN()-2)*0.1)))*$E$2*($F$2/100),2) -> 185.97 | C14: =ROUND(($C$2*(1+(-0.2+(ROW()-14)*0.1)))*($D$2*(1+(-0.2+(COLUMN()-2)*0.1)))*$E$2*($F$2/100),2) -> 209.21 | D14: =ROUND(($C$2*(1+(-0.2+(ROW()-14)*0.1)))*($D$2*(1+(-0.2+(COLUMN()-2)*0.1)))*$E$2*($F$2/100),2) -> 232.46 | E14: =ROUND(($C$2*(1+(-0.2+(ROW()-14)*0.1)))*($D$2*(1+(-0.2+(COLUMN()-2)*0.1)))*$E$2*($F$2/100),2) -> 255.7 | F14: =ROUND(($C$2*(1+(-0.2+(ROW()-14)*0.1)))*($D$2*(1+(-0.2+(COLUMN()-2)*0.1)))*$E$2*($F$2/100),2) -> 278.95
A15: AOV -10% | B15: =ROUND(($C$2*(1+(-0.2+(ROW()-14)*0.1)))*($D$2*(1+(-0.2+(COLUMN()-2)*0.1)))*$E$2*($F$2/100),2) -> 209.21 | C15: =ROUND(($C$2*(1+(-0.2+(ROW()-14)*0.1)))*($D$2*(1+(-0.2+(COLUMN()-2)*0.1)))*$E$2*($F$2/100),2) -> 235.36 | D15: =ROUND(($C$2*(1+(-0.2+(ROW()-14)*0.1)))*($D$2*(1+(-0.2+(COLUMN()-2)*0.1)))*$E$2*($F$2/100),2) -> 261.52 | E15: =ROUND(($C$2*(1+(-0.2+(ROW()-14)*0.1)))*($D$2*(1+(-0.2+(COLUMN()-2)*0.1)))*$E$2*($F$2/100),2) -> 287.67 | F15: =ROUND(($C$2*(1+(-0.2+(ROW()-14)*0.1)))*($D$2*(1+(-0.2+(COLUMN()-2)*0.1)))*$E$2*($F$2/100),2) -> 313.82
A16: AOV Base | B16: =ROUND(($C$2*(1+(-0.2+(ROW()-14)*0.1)))*($D$2*(1+(-0.2+(COLUMN()-2)*0.1)))*$E$2*($F$2/100),2) -> 232.46 | C16: =ROUND(($C$2*(1+(-0.2+(ROW()-14)*0.1)))*($D$2*(1+(-0.2+(COLUMN()-2)*0.1)))*$E$2*($F$2/100),2) -> 261.52 | D16: =ROUND(($C$2*(1+(-0.2+(ROW()-14)*0.1)))*($D$2*(1+(-0.2+(COLUMN()-2)*0.1)))*$E$2*($F$2/100),2) -> 290.57 | E16: =ROUND(($C$2*(1+(-0.2+(ROW()-14)*0.1)))*($D$2*(1+(-0.2+(COLUMN()-2)*0.1)))*$E$2*($F$2/100),2) -> 319.63 | F16: =ROUND(($C$2*(1+(-0.2+(ROW()-14)*0.1)))*($D$2*(1+(-0.2+(COLUMN()-2)*0.1)))*$E$2*($F$2/100),2) -> 348.69
A17: AOV +10% | B17: =ROUND(($C$2*(1+(-0.2+(ROW()-14)*0.1)))*($D$2*(1+(-0.2+(COLUMN()-2)*0.1)))*$E$2*($F$2/100),2) -> 255.7 | C17: =ROUND(($C$2*(1+(-0.2+(ROW()-14)*0.1)))*($D$2*(1+(-0.2+(COLUMN()-2)*0.1)))*$E$2*($F$2/100),2) -> 287.67 | D17: =ROUND(($C$2*(1+(-0.2+(ROW()-14)*0.1)))*($D$2*(1+(-0.2+(COLUMN()-2)*0.1)))*$E$2*($F$2/100),2) -> 319.63 | E17: =ROUND(($C$2*(1+(-0.2+(ROW()-14)*0.1)))*($D$2*(1+(-0.2+(COLUMN()-2)*0.1)))*$E$2*($F$2/100),2) -> 351.59 | F17: =ROUND(($C$2*(1+(-0.2+(ROW()-14)*0.1)))*($D$2*(1+(-0.2+(COLUMN()-2)*0.1)))*$E$2*($F$2/100),2) -> 383.56
A18: AOV +20% | B18: =ROUND(($C$2*(1+(-0.2+(ROW()-14)*0.1)))*($D$2*(1+(-0.2+(COLUMN()-2)*0.1)))*$E$2*($F$2/100),2) -> 278.95 | C18: =ROUND(($C$2*(1+(-0.2+(ROW()-14)*0.1)))*($D$2*(1+(-0.2+(COLUMN()-2)*0.1)))*$E$2*($F$2/100),2) -> 313.82 | D18: =ROUND(($C$2*(1+(-0.2+(ROW()-14)*0.1)))*($D$2*(1+(-0.2+(COLUMN()-2)*0.1)))*$E$2*($F$2/100),2) -> 348.69 | E18: =ROUND(($C$2*(1+(-0.2+(ROW()-14)*0.1)))*($D$2*(1+(-0.2+(COLUMN()-2)*0.1)))*$E$2*($F$2/100),2) -> 383.56 | F18: =ROUND(($C$2*(1+(-0.2+(ROW()-14)*0.1)))*($D$2*(1+(-0.2+(COLUMN()-2)*0.1)))*$E$2*($F$2/100),2) -> 418.42
A20: KEY INSIGHT METRICS
A21: Metric | B21: Value
A22: Highest LTV:CAC Channel | B22: =INDEX(A2:A7,MATCH(MAX(I2:I7),I2:I7,0)) -> Nike SNKRS App Sneakerhead
A23: Lowest LTV:CAC Channel | B23: =INDEX(A2:A7,MATCH(MIN(I2:I7),I2:I7,0)) -> Nike Direct - Owned Stores
A24: Avg D2C CLV | B24: =P2 -> 262.995
A25: Avg Wholesale CLV | B25: =AVERAGEIF(B2:B7,"Wholesale",H2:H7) -> 165.39333
A26: CLV Gap D2C vs Wholesale | B26: =B24-B25 -> 97.601667
A27: Avg D2C CAC | B27: =AVERAGEIF(B2:B7,"D2C",G2:G7) -> 41.5
A28: Avg Wholesale CAC | B28: =AVERAGEIF(B2:B7,"Wholesale",G2:G7) -> 6
A29: CAC Difference D2C vs Wholesale | B29: =B27-B28 -> 35.5

Sheet CALC_MarketReaction
A1: Event_ID | B1: Event_Date | C1: Event_Name | D1: Event_Category | E1: Decision_Type | F1: Price_On_Event | G1: Price_30d_After | H1: Price_90d_After | I1: Return_30d_Pct | J1: Return_90d_Pct | K1: Market_Verdict | L1: Verdict_Score | M1: Cumulative_Return_30d | N1: Event_Impact_Flag
A2: =RAW_Stock_Events!A2 -> 1 | B2: =RAW_Stock_Events!B2 -> 42901 | C2: =RAW_Stock_Events!C2 -> Consumer Direct Offense Announced | D2: =RAW_Stock_Events!D2 -> Strategy | E2: =RAW_Stock_Events!E2 -> Offensive | F2: =RAW_Stock_Events!F2 -> 53.2 | G2: =RAW_Stock_Events!G2 -> 58.1 | H2: =RAW_Stock_Events!H2 -> 60.2 | ... K2: =RAW_Stock_Events!K2 -> Positive | L2: =IF(K2="Positive",1,IF(K2="Negative",-1,IF(K2="Mixed",0,0))) -> 1 | M2: =I2 -> 9.2 | N2: =IF(ABS(I2)>=10,"MAJOR MOVER",IF(ABS(I2)>=5,"SIGNIFICANT","MINOR")) -> SIGNIFICANT
A3: =RAW_Stock_Events!A3 -> 2 | B3: =RAW_Stock_Events!B3 -> 43158 | C3: =RAW_Stock_Events!C3 -> Partnership with Amazon Confirmed | D3: =RAW_Stock_Events!D3 -> Partnership | E3: =RAW_Stock_Events!E3 -> Offensive | F3: =RAW_Stock_Events!F3 -> 66.5 | G3: =RAW_Stock_Events!G3 -> 69.3 | H3: =RAW_Stock_Events!H3 -> 72.1 | ... K3: =RAW_Stock_Events!K3 -> Positive | L3: =IF(K3="Positive",1,IF(K3="Negative",-1,IF(K3="Mixed",0,0))) -> 1 | M3: =M2+I3 -> 13.4 | N3: =IF(ABS(I3)>=10,"MAJOR MOVER",IF(ABS(I3)>=5,"SIGNIFICANT","MINOR")) -> MINOR
A4: =RAW_Stock_Events!A4 -> 3 | B4: =RAW_Stock_Events!B4 -> 43781 | C4: =RAW_Stock_Events!C4 -> Mark Parker Steps Down - Donahoe Named CEO | D4: =RAW_Stock_Events!D4 -> Leadership | E4: =RAW_Stock_Events!E4 -> Transition | F4: =RAW_Stock_Events!F4 -> 90.3 | G4: =RAW_Stock_Events!G4 -> 87.2 | H4: =RAW_Stock_Events!H4 -> 93.4 | ... K4: =RAW_Stock_Events!K4 -> Neutral | L4: =IF(K4="Positive",1,IF(K4="Negative",-1,IF(K4="Mixed",0,0))) -> 0 | M4: =M3+I4 -> 10 | N4: =IF(ABS(I4)>=10,"MAJOR MOVER",IF(ABS(I4)>=5,"SIGNIFICANT","MINOR")) -> MINOR
A5: =RAW_Stock_Events!A5 -> 4 | B5: =RAW_Stock_Events!B5 -> 44005 | C5: =RAW_Stock_Events!C5 -> Consumer Direct Acceleration Announced | D5: =RAW_Stock_Events!D5 -> Strategy | E5: =RAW_Stock_Events!E5 -> Acceleration | F5: =RAW_Stock_Events!F5 -> 98.3 | G5: =RAW_Stock_Events!G5 -> 110.2 | H5: =RAW_Stock_Events!H5 -> 119.4 | ... K5: =RAW_Stock_Events!K5 -> Positive | L5: =IF(K5="Positive",1,IF(K5="Negative",-1,IF(K5="Mixed",0,0))) -> 1 | M5: =M4+I5 -> 22.1 | N5: =IF(ABS(I5)>=10,"MAJOR MOVER",IF(ABS(I5)>=5,"SIGNIFICANT","MINOR")) -> MAJOR MOVER
A6: =RAW_Stock_Events!A6 -> 5 | B6: =RAW_Stock_Events!B6 -> 44518 | C6: =RAW_Stock_Events!C6 -> NKE Stock Peak ~$177 | D6: =RAW_Stock_Events!D6 -> Market | E6: =RAW_Stock_Events!E6 -> Peak | F6: =RAW_Stock_Events!F6 -> 177.5 | G6: =RAW_Stock_Events!G6 -> 155.3 | H6: =RAW_Stock_Events!H6 -> 134.2 | ... K6: =RAW_Stock_Events!K6 -> N/A - Peak | L6: =IF(K6="Positive",1,IF(K6="Negative",-1,IF(K6="Mixed",0,0))) -> 0 | M6: =M5+I6 -> 9.6 | N6: =IF(ABS(I6)>=10,"MAJOR MOVER",IF(ABS(I6)>=5,"SIGNIFICANT","MINOR")) -> MAJOR MOVER
A7: =RAW_Stock_Events!A7 -> 6 | B7: =RAW_Stock_Events!B7 -> 44736 | C7: =RAW_Stock_Events!C7 -> Inventory Crisis Disclosed in Earnings | D7: =RAW_Stock_Events!D7 -> Crisis | E7: =RAW_Stock_Events!E7 -> Warning | F7: =RAW_Stock_Events!F7 -> 109.5 | G7: =RAW_Stock_Events!G7 -> 97.3 | H7: =RAW_Stock_Events!H7 -> 85.2 | ... K7: =RAW_Stock_Events!K7 -> Negative | L7: =IF(K7="Positive",1,IF(K7="Negative",-1,IF(K7="Mixed",0,0))) -> -1 | M7: =M6+I7 -> -1.5 | N7: =IF(ABS(I7)>=10,"MAJOR MOVER",IF(ABS(I7)>=5,"SIGNIFICANT","MINOR")) -> MAJOR MOVER
A8: =RAW_Stock_Events!A8 -> 7 | B8: =RAW_Stock_Events!B8 -> 44911 | C8: =RAW_Stock_Events!C8 -> Q2 FY2023 Earnings - Inventory Glut Confirmed | D8: =RAW_Stock_Events!D8 -> Crisis | E8: =RAW_Stock_Events!E8 -> Earnings | F8: =RAW_Stock_Events!F8 -> 110.2 | G8: =RAW_Stock_Events!G8 -> 118.4 | H8: =RAW_Stock_Events!H8 -> 122.3 | ... K8: =RAW_Stock_Events!K8 -> Mixed | L8: =IF(K8="Positive",1,IF(K8="Negative",-1,IF(K8="Mixed",0,0))) -> 0 | M8: =M7+I8 -> 5.9 | N8: =IF(ABS(I8)>=10,"MAJOR MOVER",IF(ABS(I8)>=5,"SIGNIFICANT","MINOR")) -> SIGNIFICANT
A9: =RAW_Stock_Events!A9 -> 8 | B9: =RAW_Stock_Events!B9 -> 45203 | C9: =RAW_Stock_Events!C9 -> Foot Locker CEO Announces Renewed Nike Partnership | D9: =RAW_Stock_Events!D9 -> Recovery | E9: =RAW_Stock_Events!E9 -> Partnership | F9: =RAW_Stock_Events!F9 -> 88.5 | G9: =RAW_Stock_Events!G9 -> 100.2 | H9: =RAW_Stock_Events!H9 -> 105.4 | ... K9: =RAW_Stock_Events!K9 -> Positive | L9: =IF(K9="Positive",1,IF(K9="Negative",-1,IF(K9="Mixed",0,0))) -> 1 | M9: =M8+I9 -> 19.1 | N9: =IF(ABS(I9)>=10,"MAJOR MOVER",IF(ABS(I9)>=5,"SIGNIFICANT","MINOR")) -> MAJOR MOVER
A10: =RAW_Stock_Events!A10 -> 9 | B10: =RAW_Stock_Events!B10 -> 45471 | C10: =RAW_Stock_Events!C10 -> FY2024 Earnings - Revenue Growth Stalls | D10: =RAW_Stock_Events!D10 -> Crisis | E10: =RAW_Stock_Events!E10 -> Earnings | F10: =RAW_Stock_Events!F10 -> 75.3 | G10: =RAW_Stock_Events!G10 -> 72.1 | H10: =RAW_Stock_Events!H10 -> 70.2 | ... K10: =RAW_Stock_Events!K10 -> Negative | L10: =IF(K10="Positive",1,IF(K10="Negative",-1,IF(K10="Mixed",0,0))) -> -1 | M10: =M9+I10 -> 14.8 | N10: =IF(ABS(I10)>=10,"MAJOR MOVER",IF(ABS(I10)>=5,"SIGNIFICANT","MINOR")) -> MINOR
A11: =RAW_Stock_Events!A11 -> 10 | B11: =RAW_Stock_Events!B11 -> 45554 | C11: =RAW_Stock_Events!C11 -> Donahoe Replaced by Elliott Hill as CEO | D11: =RAW_Stock_Events!D11 -> Leadership | E11: =RAW_Stock_Events!E11 -> Recovery | F11: =RAW_Stock_Events!F11 -> 78.2 | G11: =RAW_Stock_Events!G11 -> 90.4 | H11: =RAW_Stock_Events!H11 -> 96.3 | ... K11: =RAW_Stock_Events!K11 -> Positive | L11: =IF(K11="Positive",1,IF(K11="Negative",-1,IF(K11="Mixed",0,0))) -> 1 | M11: =M10+I11 -> 30.4 | N11: =IF(ABS(I11)>=10,"MAJOR MOVER",IF(ABS(I11)>=5,"SIGNIFICANT","MINOR")) -> MAJOR MOVER
A12: =RAW_Stock_Events!A12 -> 11 | B12: =RAW_Stock_Events!B12 -> 45566 | C12: =RAW_Stock_Events!C12 -> Elliott Management Takes Activist Stake | D12: =RAW_Stock_Events!D12 -> Investor | E12: =RAW_Stock_Events!E12 -> External | F12: =RAW_Stock_Events!F12 -> 92.1 | G12: =RAW_Stock_Events!G12 -> 85.3 | H12: =RAW_Stock_Events!H12 -> 80.2 | ... K12: =RAW_Stock_Events!K12 -> Negative | L12: =IF(K12="Positive",1,IF(K12="Negative",-1,IF(K12="Mixed",0,0))) -> -1 | M12: =M11+I12 -> 23 | N12: =IF(ABS(I12)>=10,"MAJOR MOVER",IF(ABS(I12)>=5,"SIGNIFICANT","MINOR")) -> SIGNIFICANT
A14: MARKET REACTION SUMMARY
A15: Metric | B15: Value
A16: Total Positive Events | B16: =COUNTIF(K2:K12,"Positive") -> 5
A17: Total Negative Events | B17: =COUNTIF(K2:K12,"Negative") -> 3
A18: Avg 30d Return All Events | B18: =ROUND(AVERAGE(I2:I12),2) -> 2.09
A19: Avg 30d Return Positive Decisions | B19: =ROUND(AVERAGEIF(K2:K12,"Positive",I2:I12),2) -> 10.86
A20: Avg 30d Return Negative Decisions | B20: =ROUND(AVERAGEIF(K2:K12,"Negative",I2:I12),2) -> -7.6
A21: Worst Single Event 30d Return | B21: =ROUND(MIN(I2:I12),2) -> -12.5
A22: Best Single Event 30d Return | B22: =ROUND(MAX(I2:I12),2) -> 15.6
A23: Cumulative Return Across All Events | B23: =ROUND(SUM(I2:I12),2) -> 23
A24: Major Market Movers Count | B24: =COUNTIF(N2:N12,"MAJOR MOVER") -> 5

Sheet DASHBOARD_Summary
A1: OPTIMISED INTO OBSOLESCENCE - NIKE STRATEGIC INTELLIGENCE DASHBOARD
A2: Forensic BI Analysis | FY2015–FY2024 | Tools: SQL · Excel · Power BI
B4: PEAK REVENUE 51362 M FY2023 | F4: PEAK GROSS MARGIN 46.24% FY2022 | J4: PEAK OPERATING MARGIN 15.58% FY2021 — CDO Peak | N4: OPERATING MARGIN FY2024 12.29% vs 15.58% at peak
B8: D2C SHARE AT PEAK 43.7% FY2023 — CDO Target was 60% | F8: WHOLESALE ACCOUNTS CUT 50,000+ FY2019–FY2022 | J8: REVENUE GAP VS SCENARIO A ~$5.6B Estimated FY2024 shortfall | N8: NIKE STOCK DECLINE FROM PEAK -60.4% Nov 2021 ($177) → Jun 2024 ($70)
A13: METRIC | B13: FY2017 VALUE | C13: FY2024 VALUE | D13: DIRECTION | E13: STATUS | F13: ASSESSMENT
A14: Gross Margin % | B14: 0.4458 | C14: =INDEX(tbl_Financial[Gross_Margin_Pct],MATCH(2024,tbl_Financial[Fiscal_Year],0))&"%" -> 44.56% | D14: ↓ | E14: AMBER | F14: Margin held but below 2016 peak of 46.24%
A15: Operating Margin % | B15: 0.1383 | C15: =INDEX(tbl_Financial[Operating_Margin_Pct],MATCH(2024,tbl_Financial[Fiscal_Year],0))&"%" -> 12.29% | D15: ↓ | E15: RED | F15: Fell 354 bps from FY2021 peak despite higher D2C share
A16: D2C Revenue Share | B16: 0.324 | C16: =INDEX(tbl_Channel[Nike_Direct_Share_Pct],MATCH(2024,tbl_Channel[Fiscal_Year],0))&"%" -> 43.6% | D16: ↑ | E16: GREEN | F16: CDO objective achieved — but at operating cost
A17: Wholesale Revenue ($M) | B17: 22990 | C17: =INDEX(tbl_Channel[Wholesale_Revenue_M],MATCH(2024,tbl_Channel[Fiscal_Year],0)) -> 27758 | D17: ↑ | E17: AMBER | F17: Recovering but below optimal level; key partners still rebuilding
A18: SGA % of Revenue | B18: 0.3075 | C18: =INDEX(tbl_Financial[SGA_Pct_Revenue],MATCH(2024,tbl_Financial[Fiscal_Year],0))&"%" -> 32.27% | D18: ↑ | E18: RED | F18: Rose 1.52 pts — D2C operating costs absorbed all gross margin gains
A19: Nike Market Share % | B19: 0.382 | C19: 0.302 | D19: ↓ | E19: RED | F19: Lost 8 points to Hoka On Running New Balance since CDO launch
A20: Digital Revenue ($M) | B20: 2200 | C20: 12100 | D20: ↑ | E20: GREEN | F20: Strong digital build — the one clear CDO win
A21: LTV:CAC — Best Wholesale | B21: Est. 9.0x | C21: Est. 9.0x | D21: → | E21: GREEN | F21: Wholesale CAC near zero preserved strong LTV:CAC throughout
